LICENSE
MANIFEST.in
README.md
setup.py
test/__init__.py
test/test_act_afb.py
test/test_act_isda.py
test/test_d30360e.py
test/test_d30365.py
test/test_isaleapyear.py
test/test_julianday.py
test/test_yearfrac.py
yearfrac/__init__.py
yearfrac/act_afb.py
yearfrac/act_isda.py
yearfrac/d30360e.py
yearfrac/d30365.py
yearfrac/isaleapyear.py
yearfrac/julianday.py
yearfrac/method_factory.py
yearfrac/yearfrac.py
yearfrac.egg-info/PKG-INFO
yearfrac.egg-info/SOURCES.txt
yearfrac.egg-info/dependency_links.txt
yearfrac.egg-info/requires.txt
yearfrac.egg-info/top_level.txt
yearfrac.egg-info/zip-safe