Metadata-Version: 2.1
Name: yearfrac
Version: 0.4.8
Summary: Daycount methods to compute date differences in year units
Home-page: http://github.com/kmedian/yearfrac
Author: Ulf Hamster
Author-email: 554c46@gmail.com
License: MIT
Requires-Python: >=3.6
License-File: LICENSE
